{
  "apiVersion": "1.1.1",
  "datasets": {
    "/": {
      "label": "",
      "children": ["/entry_0000", "/entry_0001", "/entry_0002"]
    },
    "/entry_0000": {
      "label": "entry_0000",
      "children": [
        "/entry_0000/0_measurement",
        "/entry_0000/1_integration",
        "/entry_0000/program_name",
        "/entry_0000/start_time",
        "/entry_0000/title"
      ]
    },
    "/entry_0000/0_measurement": {
      "label": "0_measurement",
      "children": [
        "/entry_0000/0_measurement/diode",
        "/entry_0000/0_measurement/images",
        "/entry_0000/0_measurement/ring_curent",
        "/entry_0000/0_measurement/timestamps"
      ]
    },
    "/entry_0000/0_measurement/diode": {
      "label": "diode"
    },
    "/entry_0000/0_measurement/images": {
      "label": "images"
    },
    "/entry_0000/0_measurement/ring_curent": {
      "label": "ring_curent"
    },
    "/entry_0000/0_measurement/timestamps": {
      "label": "timestamps"
    },
    "/entry_0000/1_integration": {
      "label": "1_integration",
      "children": [
        "/entry_0000/1_integration/configuration",
        "/entry_0000/1_integration/date",
        "/entry_0000/1_integration/value"
      ]
    },
    "/entry_0000/1_integration/configuration": {
      "label": "configuration"
    },
    "/entry_0000/1_integration/date": {
      "label": "date"
    },
    "/entry_0000/1_integration/value": {
      "label": "value"
    },
    "/entry_0000/program_name": {
      "label": "program_name"
    },
    "/entry_0000/start_time": {
      "label": "start_time"
    },
    "/entry_0000/title": {
      "label": "title"
    },
    "/entry_0001": {
      "label": "entry_0001",
      "children": ["/entry_0001/program_name"]
    },
    "/entry_0001/program_name": {
      "label": "program_name"
    },
    "/entry_0002": {
      "label": "entry_0002",
      "children": ["/entry_0002/program_name"]
    },
    "/entry_0002/program_name": {
      "label": "program_name"
    }
  }
}
